[
    {
        "target_url": null,
        "threat_score": null,
        "environment_id": 100,
        "total_processes": 0,
        "threat_level": null,
        "size": 31261,
        "job_id": "5c4435ef7ca3e109e640b709",
        "vx_family": null,
        "interesting": false,
        "error_origin": null,
        "state": "IN_QUEUE",
        "mitre_attcks": [],
        "certificates": [],
        "hosts": [],
        "sha256": "26d3c8656a83b06b293b15251617fe2c2c493f842a95b3d9b2ee45b3209d5fac",
        "type": "PNG image data, 1200 x 413, 8-bit/color RGBA, non-interlaced",
        "compromised_hosts": [],
        "extracted_files": [],
        "analysis_start_time": "2019-01-20T02:50:01-06:00",
        "tags": [],
        "imphash": null,
        "total_network_connections": 0,
        "av_detect": null,
        "total_signatures": 0,
        "submit_name": "Proofpoint_R_Logo (1).png",
        "ssdeep": null,
        "classification_tags": [],
        "md5": "48703c5d4ea8dc2099c37ea871b640ef",
        "processes": [],
        "sha1": "5b30e297b54ef27ffcda06aa212b5aa6c5424e1c",
        "url_analysis": false,
        "sha512": "01f48fa1671cdc9e4d6866b9b237430f1b9b7093cbbed57fb010dc3db84a754a7a0457c5fd968d4e693ca74bdc1c7f15efb55f2af2ea236354944cffc8d4efd8",
        "file_metadata": null,
        "environment_description": "Windows 7 32 bit",
        "verdict": null,
        "domains": [],
        "error_type": null,
        "type_short": [
            "img"
        ]
    }
]